[
  { "vi": "Bạn tên là gì?", "zh": "你叫什么名字？", "py": "Nǐ jiào shénme míngzi?" },
  { "vi": "Rất vui được làm quen với bạn.", "zh": "很高兴认识你。", "py": "Hěn gāoxìng rènshi nǐ." },
  { "vi": "Bạn là người nước nào?", "zh": "你是哪 quốc rén？", "py": "Nǐ shì nǎ guó rén?" },
  { "vi": "Nhà bạn có mấy người?", "zh": "你家有几口人？", "py": "Nǐ jiā yǒu jǐ kǒu rén?" },
  { "vi": "Bạn sống ở đâu?", "zh": "你住在哪里？", "py": "Nǐ zhù zài nǎlǐ?" },
  { "vi": "Năm nay bạn bao nhiêu tuổi?", "zh": "你今年多大了？", "py": "Nǐ jīnnián duōdà le?" },
  { "vi": "Bạn làm nghề gì?", "zh": "你做什么工作？", "py": "Nǐ zuò shénme gōngzuò?" },
  { "vi": "Bạn học tiếng Trung bao lâu rồi?", "zh": "你学中文多久了？", "py": "Nǐ xué Zhōngwén duōjiǔ le?" },
  { "vi": "Tôi thấy tiếng Trung không khó lắm.", "zh": "我觉得中文不太难。", "py": "Wǒ juéde Zhōngwén bú tài nán." },
  { "vi": "Bạn nói chậm một chút được không?", "zh": "请你说慢一点儿。", "py": "Qǐng nǐ shuō màn yìdiǎnr." },
  { "vi": "Câu này nghĩa là gì?", "zh": "这个句子是什么意思？", "py": "Zhège jùzi shì shénme yìsi?" },
  { "vi": "Bạn có thể giúp tôi một chút không?", "zh": "你能帮我一下吗？", "py": "Nǐ néng bāng wǒ yíxià ma?" },
  { "vi": "Xin lỗi, tôi không hiểu bạn nói gì.", "zh": "对不起，我不明白你说什么。", "py": "Duìbuqǐ, wǒ bù míngbai nǐ shuō shénme." },
  { "vi": "Chúc bạn sinh nhật vui vẻ!", "zh": "祝你生日快乐！", "py": "Zhù nǐ shēngrì kuàilè!" },
  { "vi": "Dạo này bạn thế nào?", "zh": "你最近怎么样？", "py": "Nǐ zuìjìn zěnmeyàng?" },
  { "vi": "Gia đình bạn vẫn khỏe chứ?", "zh": "你的家人都好吗？", "py": "Nǐ de jiārén dōu hǎo ma?" },
  { "vi": "Mọi việc đều tốt cả, cảm ơn bạn.", "zh": "一切都很好，谢谢你。", "py": "Yíqiè dōu hěn hǎo, xièxie nǐ." },
  { "vi": "Khi nào bạn có thời gian rảnh?", "zh": "你什么时候有时间？", "py": "Nǐ shénme shíhou yǒu shíjiān?" },
  { "vi": "Chúng ta kết bạn WeChat nhé?", "zh": "我们加个微信吧？", "py": "Wǒmen jiā gè Wēixìn ba?" },
  { "vi": "Hẹn gặp lại bạn vào ngày mai.", "zh": "明天见。", "py": "Míngtiān jiàn." },
  { "vi": "Bạn muốn ăn gì?", "zh": "你想吃什么？", "py": "Nǐ xiǎng chī shénme?" },
  { "vi": "Cho tôi xem thực đơn một chút.", "zh": "给我看一下菜单。", "py": "Gěi wǒ kàn yíxià càidān." },
  { "vi": "Ở đây có món gì ngon không?", "zh": "这儿有什么好吃的吗？", "py": "Zhèr yǒu shénme hǎochī de ma?" },
  { "vi": "Tôi muốn gọi một bát mì bò.", "zh": "我想点一碗牛肉面。", "py": "Wǒ xiǎng diǎn yì wǎn niúròumiàn." },
  { "vi": "Bạn có ăn được cay không?", "zh": "你能吃辣吗？", "py": "Nǐ néng chī là ma?" },
  { "vi": "Đừng cho rau thơm vào nhé.", "zh": "别放香菜。", "py": "Bié fàng xiāngcài." },
  { "vi": "Cho tôi thêm một cốc nước lọc.", "zh": "请给我再来一杯白开水。", "py": "Qǐng gěi wǒ zàilái yì bēi báikāishuǐ." },
  { "vi": "Món này hơi mặn một chút.", "zh": "这个菜有点儿咸。", "py": "Zhège cài yǒudiǎnr xián." },
  { "vi": "Chúng ta đi ăn đồ ăn Trung Quốc đi.", "zh": "我们去吃中国菜吧。", "py": "Wǒmen qù chī Zhōngguó cài ba." },
  { "vi": "Chúc bạn ngon miệng!", "zh": "祝你胃口好！", "py": "Zhù nǐ wèikǒu hǎo!" },
  { "vi": "Tôi no rồi, ăn không nổi nữa.", "zh": "我饱了，吃不下了。", "py": "Wǒ bǎo le, chī bú xià le." },
  { "vi": "Phục vụ ơi, thanh toán tiền!", "zh": "服务员，买单！", "py": "Fúwùyuán, mǎidān!" },
  { "vi": "Để tôi mời khách, đừng tranh với tôi.", "zh": "我请客，别跟我抢。", "py": "Wǒ qǐngkè, bié gēn wǒ qiǎng." },
  { "vi": "Chúng ta chia tiền đi.", "zh": "我们 AA 吧。", "py": "Wǒmen AA ba." },
  { "vi": "Đồ ăn ở đây vừa rẻ vừa ngon.", "zh": "这里的菜又便宜又好吃。", "py": "Zhèlǐ de cài yòu piányi yòu hǎochī." },
  { "vi": "Cái này bao nhiêu tiền?", "zh": "这个多少钱？", "py": "Zhège duōshǎo qián?" },
  { "vi": "Đắt quá, bớt một chút đi.", "zh": "太贵了，便宜点儿吧。", "py": "Tài guì le, piányi diǎnr ba." },
  { "vi": "Bạn có cỡ to hơn không?", "zh": "你有大号的吗？", "py": "Nǐ yǒu dàhào de ma?" },
  { "vi": "Tôi có thể mặc thử bộ này không?", "zh": "我可以试穿一下吗？", "py": "Wǒ kěyǐ shìchuān yíxià ma?" },
  { "vi": "Màu này không hợp với tôi lắm.", "zh": "这个颜色不太适合我。", "py": "Zhège yánsè bútài shìhé wǒ." },
  { "vi": "Tôi muốn mua một món quà cho mẹ.", "zh": "我想给妈妈买个礼物。", "py": "Wǒ xiǎng gěi māma mǎi gè lǐwù." },
  { "vi": "Ở đây có thanh toán bằng thẻ không?", "zh": "这里可以刷卡吗？", "py": "Zhèlǐ kěyǐ shuākǎ ma?" },
  { "vi": "Cho tôi một cái túi nilon.", "zh": "给我一个塑料袋。", "py": "Gěi wǒ yígè sùliàodài." },
  { "vi": "Tôi chỉ xem một chút thôi.", "zh": "我只是随便看看。", "py": "Wǒ zhǐshì suíbiàn kànkan." },
  { "vi": "Chất lượng cái này rất tốt.", "zh": "这个质量很好。", "py": "Zhège zhìliàng hěn hǎo." },
  { "vi": "Bạn có màu khác không?", "zh": "你有别的颜色吗？", "py": "Nǐ yǒu bié de yánsè ma?" },
  { "vi": "Tôi lấy cái này, gói lại giúp tôi.", "zh": "我要这个，帮我包一下。", "py": "Wǒ yào zhège, bāng wǒ bāo yíxià." },
  { "vi": "Cửa hàng mấy giờ đóng cửa?", "zh": "商店几点关门？", "py": "Shāngdiàn jǐ diǎn guānmén?" },
  { "vi": "Hôm nay có giảm giá không?", "zh": "今天打折吗？", "py": "Jīntiān dǎzhé ma?" },
  { "vi": "Rẻ quá, tôi sẽ mua hai cái.", "zh": "太便宜了，我买两个。", "py": "Tài piányi le, wǒ mǎi liǎng gè." },
  { "vi": "Bây giờ là mấy giờ?", "zh": "现在几点？", "py": "Xiànzài jǐ diǎn?" },
  { "vi": "Hôm nay là thứ mấy?", "zh": "今天星期几？", "py": "Jīntiān xīngqījǐ?" },
  { "vi": "Ngày mai bạn có bận không?", "zh": "明天 nǐ máng ma？", "py": "Míngtiān nǐ máng ma?" },
  { "vi": "Thời tiết hôm nay đẹp quá!", "zh": "今天天气太好了！", "py": "Jīntiān tiānqì tài hǎo le!" },
  { "vi": "Nghe nói chiều nay sẽ có mưa.", "zh": "听说今天下午会有雨。", "py": "Tīngshuō jīntiān xiàwǔ huì yǒu yǔ." },
  { "vi": "Bạn nhớ mang theo ô nhé.", "zh": "记得带伞。", "py": "Jìde dài sǎn." },
  { "vi": "Mùa hè ở đây rất nóng.", "zh": "这里的夏天很热。", "py": "Zhèlǐ de xiàtiān hěn rè." },
  { "vi": "Tôi thích nhất là mùa thu.", "zh": "我最喜欢秋天。", "py": "Wǒ zuì xǐhuan qiūtiān." },
  { "vi": "Sắp đến Tết rồi.", "zh": "快要过年了。", "py": "Kuàiyào guònián le." },
  { "vi": "Hôm nay nhiệt độ bao nhiêu?", "zh": "今天多少度？", "py": "Jīntiān duōshǎo dù?" },
  { "vi": "Sáng sớm tôi thường dậy lúc 6 giờ.", "zh": "我早上常常六点起床。", "py": "Wǒ zǎoshang chángcháng liù diǎn qǐchuáng." },
  { "vi": "Bạn thường làm gì vào cuối tuần?", "zh": "你周末常常做什么？", "py": "Nǐ zhōumò chángcháng zuò shénme?" },
  { "vi": "Đợi tôi 5 phút nhé.", "zh": "等我五分钟。", "py": "Děng wǒ wǔ fēnzhōng." },
  { "vi": "Đừng đến muộn đấy.", "zh": "别迟到。", "py": "Bié chídào." },
  { "vi": "Thời gian trôi nhanh quá!", "zh": "时间过得真快！", "py": "Shíjiān guò de zhēn kuài!" },
  { "vi": "Công ty của bạn ở đâu?", "zh": "你的公司在哪儿？", "py": "Nǐ de gōngsī zài nǎr?" },
  { "vi": "Bạn làm việc ở đó bao lâu rồi?", "zh": "你在那儿工作多久了？", "py": "Nǐ zài nàr gōngzuò duōjiǔ le?" },
  { "vi": "Công việc của tôi rất bận.", "zh": "我的工作很忙。", "py": "Wǒ de gōngzuò hěn máng." },
  { "vi": "Tôi thường xuyên phải tăng ca.", "zh": "我经常要加班。", "py": "Wǒ jīngcháng yào jiābān." },
  { "vi": "Sếp của bạn là người thế nào?", "zh": "你的老板是一个怎么样的人？", "py": "Nǐ de lǎobǎn shì yígè zěnmeyàng de rén?" },
  { "vi": "Tôi muốn xin nghỉ phép một ngày.", "zh": "我想请一天假。", "py": "Wǒ xiǎng qǐng yì tiān jià." },
  { "vi": "Ngày mai tôi có một cuộc họp.", "zh": "明天我有一个会议。", "py": "Míngtiān wǒ yǒu yígè huìyì." },
  { "vi": "Bạn học chuyên ngành gì?", "zh": "你学什么专业？", "py": "Nǐ xué shénme zhuānyè?" },
  { "vi": "Bài tập về nhà bạn làm xong chưa?", "zh": "你的作业做完了吗？", "py": "Nǐ de zuòyè zuòwán le ma?" },
  { "vi": "Kỳ thi lần này rất quan trọng.", "zh": "这次考试很重要。", "py": "Zhè cì kǎoshì hěn zhòngyào." },
  { "vi": "Tôi muốn tìm một công việc mới.", "zh": "我想找一份新工作。", "py": "Wǒ xiǎng zhǎo yí fèn xīn gōngzuò." },
  { "vi": "Chúc bạn công việc thuận lợi.", "zh": "祝你工作顺利。", "py": "Zhù nǐ gōngzuò shùnlì." },
  { "vi": "Anh ấy là đồng nghiệp của tôi.", "zh": "他是我的同事。", "py": "Tā shì wǒ de tóngshì." },
  { "vi": "Tôi vẫn đang suy nghĩ về vấn đề này.", "zh": "我还在考虑这个问题。", "py": "Wǒ hái zài kǎolǜ zhège wèntí." },
  { "vi": "Bạn có kế hoạch gì cho tương lai không?", "zh": "你对未来有什么计划吗？", "py": "Nǐ duì wèilái yǒu shénme jìhuà ma?" },
  { "vi": "Sở thích của bạn là gì?", "zh": "你的爱好是什么？", "py": "Nǐ de àihào shì shénme?" },
  { "vi": "Tôi thích nghe nhạc và xem phim.", "zh": "我喜欢听音乐和看电影。", "py": "Wǒ xǐhuan tīng yīnyuè hé kàn diànyǐng." },
  { "vi": "Bạn có biết chơi bóng đá không?", "zh": "你会踢足球吗？", "py": "Nǐ huì tī zúqiú ma?" },
  { "vi": "Tôi thường đi chạy bộ vào buổi sáng.", "zh": "我早上经常去跑步。", "py": "Wǒ zǎoshang jīngcháng qù pǎobù." },
  { "vi": "Bạn thích xem loại phim nào?", "zh": "你喜欢看什么样的电影？", "py": "Nǐ xǐhuan kàn shénmeyàng de diànyǐng?" },
  { "vi": "Quyển sách này rất thú vị.", "zh": "这本书很有意思。", "py": "Zhè běn shū hěn yǒu yìsi." },
  { "vi": "Tôi muốn đi du lịch Trung Quốc.", "zh": "我想去中国旅游。", "py": "Wǒ xiǎng qù Zhōngguó lǚyóu." },
  { "vi": "Bạn đã từng đi Bắc Kinh chưa?", "zh": "你去过北京吗？", "py": "Nǐ qùguo Běijīng ma?" },
  { "vi": "Phong cảnh ở đó rất đẹp.", "zh": "那里的风景很美。", "py": "Nàlǐ de fēngjǐng hěn měi." },
  { "vi": "Tôi hơi mệt, muốn đi ngủ sớm.", "zh": "我有点儿累，想早点儿睡觉。", "py": "Wǒ yǒudiǎnr lèi, xiǎng zǎodiǎnr shuìjiào." },
  { "vi": "Bạn đang làm gì thế?", "zh": "你在做什么呢？", "py": "Nǐ zài zuò shénme ne?" },
  { "vi": "Tôi đang nấu cơm.", "zh": "我在做饭。", "py": "Wǒ zài zuòfàn." },
  { "vi": "Đừng lo lắng, mọi chuyện sẽ ổn thôi.", "zh": "别担心，一切都会好的。", "py": "Bié dānxīn, yíqiè dūhuì hǎo de." },
  { "vi": "Bạn cảm thấy thế nào?", "zh": "你觉得怎么样？", "py": "Nǐ juéde zěnmeyàng?" },
  { "vi": "Tôi thấy hơi đau đầu.", "zh": "我觉得头有点儿疼。", "py": "Wǒ juéde tóu yǒudiǎnr téng." },
  { "vi": "Bạn nên đi bệnh viện khám xem sao.", "zh": "你应该去医院看看。", "py": "Nǐ yīnggāi qù yīyuàn kànkan." },
  { "vi": "Nhớ uống nhiều nước nhé.", "zh": "记得多喝水。", "py": "Jìde duō hē shuǐ." },
  { "vi": "Chúc bạn mau khỏe lại.", "zh": "祝你早日康复。", "py": "Zhù nǐ zǎorì kāngfù." },
  { "vi": "Cảm ơn sự giúp đỡ của bạn.", "zh": "谢谢你的帮助。", "py": "Xièxie nǐ de bāngzhù." },
  { "vi": "Thật là một ngày tuyệt vời!", "zh": "真是美好的一天！", "py": "Zhēnshì měihǎo de yìtiān!" },
  { "vi": "Bạn đem cuốn sách này trả cho thư viện đi.", "zh": "你把这本书还给图书馆吧。", "py": "Nǐ bǎ zhè běn shū huán gěi túshūguǎn ba." },
  { "vi": "Máy tính của tôi bị em trai dùng hỏng rồi.", "zh": "我的电脑被弟弟弄坏了。", "py": "Wǒ de diànnǎo bèi dìdi nòng huài le." },
  { "vi": "Mặc dù trời mưa rất to nhưng anh ấy vẫn đi làm.", "zh": "虽然雨很大，但是他还是去上班了。", "py": "Suīrán yǔ hěn dà, dànshì tā háishì qù shàngbān le." },
  { "vi": "Tiếng Trung của cô ấy càng ngày càng tốt.", "zh": "她的汉语越来越好。", "py": "Tā de Hànyǔ yuèláiyuè hǎo." },
  { "vi": "Bạn đã dọn dẹp phòng sạch sẽ chưa?", "zh": "你把房间打扫干净了吗？", "py": "Nǐ bǎ fángjiān dǎsǎo gānjìng le ma?" },
  { "vi": "Tôi vừa về đến nhà thì trời mưa.", "zh": "我刚到家就下雨了。", "py": "Wǒ gāng dào jiā jiù xià yǔ le." },
  { "vi": "Món ăn mẹ nấu càng ăn càng thấy ngon.", "zh": "妈妈做的菜越吃越好吃。", "py": "Māma zuò de cài yuè chī yuè hǎochī." },
  { "vi": "Bạn thấy bộ phim này thế nào?", "zh": "你觉得这部电影怎么样？", "py": "Nǐ juéde zhè bù diànyǐng zěnmeyàng?" },
  { "vi": "Đừng quên mang theo hộ chiếu và vé máy bay.", "zh": "别忘了带护照和机票。", "py": "Bié wàng le dài hùzhào hé jīpiào." },
  { "vi": "Bên ngoài lạnh quá, bạn mau vào phòng đi.", "zh": "外面太冷了，你快进房间来吧。", "py": "Wàimiàn tài lěng le, nǐ kuài jìn fángjiān lái ba." },
  { "vi": "Tôi vẫn chưa chuẩn bị xong cho chuyến du lịch.", "zh": "我还没准备好去旅游的事。", "py": "Wǒ hái méi zhǔnbèi hǎo qù lǚyóu de shì." },
  { "vi": "Cuối tuần bạn thường tự nấu cơm hay đi ăn ngoài?", "zh": "周末你经常自己做饭还是出去吃？", "py": "Zhōumò nǐ jīngcháng zìjǐ zuòfàn háishì chūqù chī?" },
  { "vi": "Cái bánh kem này là bạn tự tay làm à?", "zh": "这个蛋糕是你亲手做的吗？", "py": "Zhège dàngāo shì nǐ qīnshǒu zuò de ma?" },
  { "vi": "Anh ấy chạy nhanh hơn tôi rất nhiều.", "zh": "他跑得比我快得多。", "py": "Tā pǎo de bǐ wǒ kuài de duō." },
  { "vi": "Bạn có biết hiệu sách gần đây nhất ở đâu không?", "zh": "你知道最近的书店在哪儿吗？", "py": "Nǐ zhīdào zuìjìn de shūdiàn zài nǎr ma?" },
  { "vi": "Tôi mệt đến mức không muốn nói chuyện nữa.", "zh": "我累得不想说话了。", "py": "Wǒ lèi de bù xiǎng shuōhuà le." },
  { "vi": "Tiền ở trên bàn bị ai lấy đi rồi?", "zh": "桌子上的钱被谁拿走了？", "py": "Zhuōzi shàng de qián bèi shéi názǒu le?" },
  { "vi": "Cô ấy không những xinh đẹp mà còn rất thông minh.", "zh": "她不但漂亮而且很聪明。", "py": "Tā búdàn piàoliang érqiě hěn cōngmíng." },
  { "vi": "Bạn đợi tôi một lát, tôi đi thay quần áo.", "zh": "你等我一下，我去换件衣服。", "py": "Nǐ děng wǒ yíxià, wǒ qù huàn jiàn yīfu." },
  { "vi": "Lúc rảnh rỗi tôi thích đi dạo trong công viên.", "zh": "休息的时候我喜欢去公园散步。", "py": "Xiūxi de shíhou wǒ xǐhuan qù gōngyuán sànbù." },
  { "vi": "Bạn có thể chỉ cho tôi cách đến ngân hàng không?", "zh": "你可以告诉我怎么去银行吗？", "py": "Nǐ kěyǐ gàosu wǒ zěnme qù yínháng ma?" },
  { "vi": "Trà ở đây miễn phí, bạn cứ tự nhiên.", "zh": "这里的茶是免费的，你随便喝。", "py": "Zhèlǐ de chá shì miǎnfèi de, nǐ suíbiàn hē." },
  { "vi": "Tôi quên mất hôm nay có bài kiểm tra.", "zh": "我忘了今天有考试。", "py": "Wǒ wàng le jīntiān yǒu kǎoshì." },
  { "vi": "Bạn đã xem xong cuốn tạp chí này chưa?", "zh": "你看完这本杂志了吗？", "py": "Nǐ kànwán zhè běn zázhì le ma?" },
  { "vi": "Bệnh của anh ấy đã khỏi hoàn toàn chưa?", "zh": "他的病全好了吗？", "py": "Tā de bìng quán hǎo le ma?" },
  { "vi": "Ngôi nhà này do một người bạn của tôi thiết kế.", "zh": "这个房子是我一个朋友设计的。", "py": "Zhège fángzi shì wǒ yígè péngyou shèjì de." },
  { "vi": "Bạn nên uống thuốc đúng giờ.", "zh": "你应该按时吃药。", "py": "Nǐ yīnggāi ànshí chī yào." },
  { "vi": "Tôi cảm thấy môi trường ở đây rất trong lành.", "zh": "我觉得这里的环境很干净。", "py": "Wǒ juéde zhèlǐ de huánjìng hěn gānjìng." },
  { "vi": "Bạn thích con mèo đen hay con mèo trắng?", "zh": "你喜欢黑猫还是白猫？", "py": "Nǐ xǐhuan hēimāo háishì báimāo?" },
  { "vi": "Cái vali này nặng quá, tôi xách không nổi.", "zh": "这个行李箱太重了，我拿不动。", "py": "Zhège xínglixiāng tài zhòng le, wǒ nábúdòng." },
  { "vi": "Đừng vừa ăn vừa xem điện thoại.", "zh": "别边吃饭边看手机。", "py": "Bié biān chīfàn biān kàn shǒujī." },
  { "vi": "Hôm nay tôi quên mang theo ví tiền rồi.", "zh": "我今天忘了带钱包了。", "py": "Wǒ jīntiān wàng le dài qiánbāo le." },
  { "vi": "Bạn giúp tôi rót một ly nước được không?", "zh": "你帮我倒一杯水好吗？", "py": "Nǐ bāng wǒ dào yì bēi shuǐ hǎo ma?" },
  { "vi": "Anh ấy không đồng ý với kế hoạch của tôi.", "zh": "他不同意我的计划。", "py": "Tā bù tóngyì wǒ de jìhuà." },
  { "vi": "Gần đây có siêu thị nào không?", "zh": "附近有超市吗？", "py": "Fùjìn yǒu chāoshì ma?" },
  { "vi": "Tôi đã quen với cuộc sống ở đây rồi.", "zh": "我已经习惯这里的生活了。", "py": "Wǒ yǐjīng xíguàn zhèlǐ de shēnghuó le." },
  { "vi": "Tivi bị trẻ con làm hỏng rồi.", "zh": "电视机被孩子弄坏了。", "py": "Diànshìjī bèi háizi nòng huài le." },
  { "vi": "Bạn đã chọn được món quà nào chưa?", "zh": "你选好礼物了吗？", "py": "Nǐ xuǎnhǎo lǐwù le ma?" },
  { "vi": "Món quà này thực sự rất đặc biệt.", "zh": "这个礼物真的很特别。", "py": "Zhège lǐwù zhēnde hěn tèbié." },
  { "vi": "Tôi nghĩ chúng ta nên đi bằng tàu cao tốc.", "zh": "我觉得 chúng ta 应该坐高铁去。", "py": "Wǒ juéde wǒmen yīnggāi zuò gāotiě qù." },
  { "vi": "Bạn đã gặp sếp mới chưa?", "zh": "你见到新老板了吗？", "py": "Nǐ jiàndào xīn lǎobǎn le ma?" },
  { "vi": "Chuyện này không thể trách anh ấy được.", "zh": "这件事不能怪他。", "py": "Zhè jiàn shì bùnéng guài tā." },
  { "vi": "Mọi người đều phản đối quyết định này.", "zh": "大家都反对这个决定。", "py": "Dàjiā dōu fǎnduì zhège juédìng." },
  { "vi": "Tôi hy vọng năm sau có thể thăng chức.", "zh": "我希望明年能升职。", "py": "Wǒ xīwàng míngnián néng shēngzhí." },
  { "vi": "Bạn có bằng lái xe không?", "zh": "你有驾照吗？", "py": "Nǐ yǒu jiàzhào ma?" },
  { "vi": "Chúng tôi đã cùng nhau vượt qua khó khăn.", "zh": "我们一起克服了困难。", "py": "Wǒmen yìqǐ kèfú le kùnnan." },
  { "vi": "Hôm nay tôi có rất nhiều việc phải làm.", "zh": "我今天有很多事要做。", "py": "Wǒ jīntiān yǒu hěnduō shì yào zuò." },
  { "vi": "Đừng lo, mọi thứ đã có tôi sắp xếp.", "zh": "别担心，一切有我安排。", "py": "Bié dānxīn, yíqiè yǒu wǒ ānpái." },
  { "vi": "Bạn có thích leo núi không?", "zh": "你喜欢爬山吗？", "py": "Nǐ xǐhuan páshān ma?" },
  { "vi": "Cảnh đêm ở đây đẹp không tả xiết.", "zh": "这里的夜景漂亮极了。", "py": "Zhèlǐ de yèjǐng piàoliang jíle." },
  { "vi": "Tôi cảm thấy rất xấu hổ.", "zh": "我觉得很不好意思。", "py": "Wǒ juéde hěn bù hǎoyìsi." },
  { "vi": "Anh ấy là một người rất thành thật.", "zh": "他是一个很诚实的人。", "py": "Tā shì yígè hěn chéngshí de rén." },
  { "vi": "Bạn có biết chơi cờ tướng không?", "zh": "你会下象棋吗？", "py": "Nǐ huì xià xiàngqí ma?" },
  { "vi": "Tôi muốn mua một căn nhà có ban công.", "zh": "我想买一个有阳台的房子。", "py": "Wǒ xiǎng mǎi yígè yǒu yángtái de fángzi." },
  { "vi": "Máy bay sẽ hạ cánh đúng giờ chứ?", "zh": "飞机会准时起飞吗？", "py": "Fēijī huì zhǔnshí qǐfēi ma?" },
  { "vi": "Anh ấy luôn giúp đỡ người khác.", "zh": "他总是帮助别人。", "py": "Tā zǒngshì bāngzhù biérén." },
  { "vi": "Tôi đã tìm khắp nơi nhưng không thấy chìa khóa.", "zh": "我找遍了所有地方也没找到钥匙。", "py": "Wǒ zhǎobiàn le suǒyǒu dìfang yě méi zhǎodào yàoshi." },
  { "vi": "Bạn có nghe hiểu anh ấy đang nói gì không?", "zh": "你听得懂他在说什么吗？", "py": "Nǐ tīng de dǒng tā zài shuō shénme ma?" },
  { "vi": "Cuốn sách này tôi đã đọc ba lần rồi.", "zh": "这本书我看过三次了。", "py": "Zhè běn shū wǒ kànguo sān cì le." },
  { "vi": "Tôi quyết định giảm cân từ ngày mai.", "zh": "我决定从明天开始减肥。", "py": "Wǒ juédìng cóng míngtiān kāishǐ jiǎnféi." },
  { "vi": "Đừng quá lo lắng về tương lai.", "zh": "别太担心未来。", "py": "Bié tài dānxīn wèilái." },
  { "vi": "Mọi người đều phải tuân thủ luật lệ.", "zh": "大家都必须遵守规则。", "py": "Dàjiā dōu bìxū zūnshǒu guīzé." },
  { "vi": "Anh ấy rất giỏi giải quyết vấn đề.", "zh": "他很擅长解决问题。", "py": "Tā hěn shàncháng jiějué wèntí." },
  { "vi": "Bạn có thích đi bảo tàng không?", "zh": "你喜欢去博物馆吗？", "py": "Nǐ xǐhuan qù bówùguǎn ma?" },
  { "vi": "Sức khỏe là điều quan trọng nhất.", "zh": "健康是最重要的。", "py": "Jiànkāng shì zuì zhòngyào de." },
  { "vi": "Tôi sẽ luôn ủng hộ quyết định của bạn.", "zh": "我会一直支持你的决定。", "py": "Wǒ huì yìzhí zhīchí nǐ de juédìng." },
  { "vi": "Bạn đã bao giờ đi lặn biển chưa?", "zh": "你过去潜水吗？", "py": "Nǐ guòqù qiánshuǐ ma?" },
  { "vi": "Tôi cần thời gian để suy nghĩ kỹ.", "zh": "我需要时间好好考虑。", "py": "Wǒ xūyào shíjiān hǎohǎo kǎolǜ." },
  { "vi": "Đừng bao giờ từ bỏ ước mơ của mình.", "zh": "永远不要放弃自己的梦想。", "py": "Yǒngyuǎn búyào fàngqì zìjǐ de mèngxiǎng." },
  { "vi": "Anh ấy là một người bạn rất đáng tin cậy.", "zh": "他是一个很可靠的朋友。", "py": "Tā shì yígè hěn kěkào de péngyou." },
  { "vi": "Bạn có biết nấu món ăn Việt Nam không?", "zh": "你会做越南菜吗？", "py": "Nǐ huì zuò Yuènán cài ma?" },
  { "vi": "Cuộc sống luôn đầy rẫy những bất ngờ.", "zh": "生活总是充满惊喜。", "py": "Shēnghuó zǒngshì chōngmǎn jīngxǐ." },
  { "vi": "Tôi muốn học thêm một nhạc cụ mới.", "zh": "我想学一种新的乐器。", "py": "Wǒ xiǎng xué yì zhǒng xīn de yuèqì." },
  { "vi": "Bạn có thường xuyên đi xem hòa nhạc không?", "zh": "你经常去听音乐会吗？", "py": "Nǐ jīngcháng qù tīng yīnyuèhuì ma?" },
  { "vi": "Tôi cảm thấy rất tự hào về bạn.", "zh": "我为你感到很骄傲。", "py": "Wǒ wèi nǐ gǎndào hěn jiāo'ào." },
  { "vi": "Mọi khó khăn rồi sẽ qua đi.", "zh": "所有的困难都会过去的。", "py": "Suǒyǒu de kùnnan dūhuì guòqù de." },
  { "vi": "Bạn có kế hoạch gì cho kỳ nghỉ hè này?", "zh": "这个暑假你有什么计划？", "py": "Zhège shǔjià nǐ yǒu shénme jìhuà?" },
  { "vi": "Tôi thích đi dạo dọc bờ biển.", "zh": "我喜欢沿着海边散步。", "py": "Wǒ xǐhuan yánzhe hǎibiān sànbù." },
  { "vi": "Đừng quá khắt khe với bản thân.", "zh": "别对自己太严格了。", "py": "Bié duì zìjǐ tài yángé le." },
  { "vi": "Anh ấy là người hài hước nhất tôi từng biết.", "zh": "他是我认识的最幽默的人。", "py": "Tā shì wǒ rènshi de zuì yōumò de rén." },
  { "vi": "Bạn có biết trung tâm thương mại ở đâu không?", "zh": "你知道购物中心在哪里吗？", "py": "Nǐ zhīdào gòuwù zhōngxīn zài nǎlǐ ma?" },
  { "vi": "Tôi muốn đi xem triển lãm tranh.", "zh": "我想去看画展。", "py": "Wǒ xiǎng qù kàn huàzhǎn." },
  { "vi": "Hãy trân trọng những gì mình đang có.", "zh": "珍惜你现在拥有的一切。", "py": "Zhēnxī nǐ xiànzài yōngyǒu de yíqiè." },
  { "vi": "Tôi cảm thấy rất thoải mái khi ở đây.", "zh": "我在这里觉得很舒服。", "py": "Wǒ zài zhèlǐ juéde hěn shūfu." },
  { "vi": "Bạn có muốn tham gia câu lạc bộ của chúng tôi không?", "zh": "你愿意加入我们的俱乐部吗？", "py": "Nǐ yuànyì jiārù wǒmen de jùlèbù ma?" },
  { "vi": "Tôi sẽ cố gắng hết sức để hoàn thành nhiệm vụ.", "zh": "我会尽力完成任务。", "py": "Wǒ huì jìnlì wánchéng rènwu." },
  { "vi": "Đừng để lãng phí thời gian.", "zh": "别浪费时间。", "py": "Bié làngfèi shíjiān." },
  { "vi": "Anh ấy là một giáo viên rất kiên nhẫn.", "zh": "他是一个很有耐心的老师。", "py": "Tā shì yígè hěn yǒu nàixīn de lǎoshī." },
  { "vi": "Bạn có thích ăn đồ ngọt không?", "zh": "你喜欢吃甜食吗？", "py": "Nǐ xǐhuan chī tiánshí ma?" },
  { "vi": "Tôi muốn học cách làm bánh mì.", "zh": "我想学习怎么做面包。", "py": "Wǒ xiǎng xuéxí zěnme zuò miànbāo." },
  { "vi": "Cuộc sống cần có sự cân bằng.", "zh": "生活需要平衡。", "py": "Shēnghuó xūyào pínghéng." },
  { "vi": "Tôi cảm thấy rất may mắn khi gặp được bạn.", "zh": "遇到你我觉得很幸运。", "py": "Yùdào nǐ wǒ juéde hěn xìngyùn." },
  { "vi": "Đừng ngại đặt câu hỏi nếu bạn không hiểu.", "zh": "如果不明白，别害怕提问。", "py": "Rúguǒ bù míngbai, bié hàipà tíwèn." },
  { "vi": "Anh ấy luôn giữ lời hứa.", "zh": "他总是守信用。", "py": "Tā zǒngshì shǒu xìnyòng." },
  { "vi": "Bạn có thích đi rạp chiếu phim không?", "zh": "你喜欢去电影院吗？", "py": "Nǐ xǐhuan qù diànyǐngyuàn ma?" },
  { "vi": "Tôi muốn đi du học ở Trung Quốc.", "zh": "我想去中国留学。", "py": "Wǒ xiǎng qù Zhōngguó liúxué." },
  { "vi": "Hãy luôn giữ nụ cười trên môi.", "zh": "保持微笑。", "py": "Bǎochí wēixiào." },
  { "vi": "Tôi cảm thấy rất hào hứng về chuyến đi này.", "zh": "我对这次旅行感到很兴奋。", "py": "Wǒ duì zhè cì lǚxíng gǎndào hěn xīngfèn." },
  { "vi": "Bạn có biết cách sử dụng phần mềm này không?", "zh": "你知道怎么用这个软件吗？", "py": "Nǐ zhīdào zěnme yòng zhège ruǎnjiàn ma?" },
  { "vi": "Mọi thứ đều có thể nếu chúng ta cố gắng.", "zh": "只要努力，一切皆有可能。", "py": "Zhǐyào nǔlì, yíqiè jiē yǒu kěnéng." }
]
